DaVinci/Decode_INST.v
/*
File Name   : Decode_INST.v
Description : RISC-V RV32I 译码器
Written By  : Tealer Guo
Data        : 2019/04/29
*/
module Decode_INST(
		// input clk,
		input [31:0] inst,

		output reg[9:0] alu_op,
		output reg[4:0] rs1,
		output reg[4:0] rs2,
		output reg[4:0] rd,
		output reg[31:0] address_imm,
		output reg[4:0] ls_op,
		output reg[4:0] j_op,
		output reg[4:0] b_op
	);
	
	// clk预留
	reg[31:0] immr;

	always @* begin
		address_imm<=immr;
	end
	// always @(posedge clk) begin
	// 	address_imm<=immr;
	// end

	always @* begin
		case(inst[6:0])
			// R-type decoder
			7'b0110011:begin
			rs1=inst[19:15];
			rs2=inst[24:20];
			rd=inst[11:7];
			b_op={5{1'b1}};
			ls_op={5{1'b1}};
			j_op={5{1'b1}};
			immr={32{1'b0}};
				case(inst[31:25])
					7'b0000000:begin
						case(inst[14:12])
							3'b000:begin // add
								alu_op=10'b0000000001;
							end
							3'b001:begin // sll
								alu_op=10'b0000000011;
							end
							3'b010:begin // slt
								alu_op=10'b0000000101;
							end
							3'b011:begin // sltu
								alu_op=10'b0000000110;
							end
							3'b100:begin // xor
								alu_op=10'b0000000111;
							end
							3'b101:begin // srl
								alu_op=10'b0000001000;
							end
							3'b110:begin // or
								alu_op=10'b0000001010;
							end
							3'b111:begin // and
								alu_op=10'b0000001011;
							end
						endcase
					end
					7'b0100000:begin
						case(inst[14:12])
							3'b000:begin // sub
								alu_op=10'b0000000010;
							end
							3'b101:begin // sra
								alu_op=10'b0000001001;
							end
						endcase
					end
				endcase
			end
			// I-type decoder
			7'b0010011:begin
				rs1=inst[19:15];
				rs2={5{1'b0}};
				rd=inst[11:7];
				b_op={5{1'b1}};
				ls_op={5{1'b1}};
				j_op={5{1'b1}};
				case(inst[14:12])
					3'b000:begin // addi
						alu_op=10'b1000000001;
						immr={{20{inst[31]}},inst[31:20]};
					end
					3'b010:begin // slti
						alu_op=10'b1000000101;
						immr={{20{inst[31]}},inst[31:20]};
					end
					3'b011:begin // sltiu
						alu_op=10'b1000000110;
						immr={{20{inst[31]}},inst[31:20]};
					end
					3'b100:begin // xori
						alu_op=10'b1000000111;
						immr={{20{inst[31]}},inst[31:20]};
					end
					3'b110:begin // ori
						alu_op=10'b1000001010;
						immr={{20{inst[31]}},inst[31:20]};
					end
					3'b111:begin // andi
						alu_op=10'b1000001011;
						immr={{20{inst[31]}},inst[31:20]};
					end
				endcase
				// RV64I预留
				// slli,srli,srai高位处理
				case(inst[31:25])
					7'b0000000:begin
						case(inst[14:12])
							3'b001:begin // slli
								if(inst[24]==1'b0) begin
									alu_op=10'b1000000011;
									immr=inst[24:20];
								end
							end
							3'b001:begin // srli
								if(inst[24]==1'b0) begin
									alu_op=10'b1000001000;
									immr=inst[24:20];
								end
							end
							3'b101:begin // srai
								if(inst[24]==1'b0) begin
									alu_op=10'b1000001001;
									immr=inst[24:20];
								end
							end
						endcase
					end
				endcase
			end
			// I-type decoder
			// load
			7'b0000011:begin
				rs1=inst[19:15];
				rd=inst[11:7];
				rs2=inst[24:20];
				alu_op={10{1'b1}};
				ls_op={5{1'b1}};
				j_op={5{1'b1}};
				case(inst[14:12])
					3'b000:begin // lb
						immr={{20{inst[31]}},inst[31:20]};
						ls_op=5'b00001;
					end
					3'b001:begin // lh
						immr={{20{inst[31]}},inst[31:20]};
						ls_op=5'b00010;
					end
					3'b010:begin // lw
						immr={{20{inst[31]}},inst[31:20]};
						ls_op=5'b00011;
					end
					3'b100:begin // lbu
						immr={{20{1'b0}},inst[31:20]};
						ls_op=5'b00001;
					end
					3'b101:begin // lhu
						immr={{20{1'b0}},inst[31:20]};
						ls_op=5'b00010;
					end
				endcase
			end
			// I-type decoder
			7'b1100111:begin
				rs1=inst[19:15];
				rs2={5{1'b0}};
				rd=inst[11:7];
				alu_op={10{1'b1}};
				b_op={5{1'b1}};
				ls_op={5{1'b1}};
				// RV64I预留
				case(inst[14:12])
					3'b000:begin // jalr
						immr={{20{inst[31]}},inst[31:20]};
						j_op=5'b00001;
					end
				endcase
			end
			// I-type fence
			7'b0001111:begin
				// NULL
			end
			// I-type e/csr
			7'b1110011:begin
				// NULL
			end
			// J-type decoder
			7'b1101111:begin
				rs1={5{1'b0}};
				rs2={5{1'b0}};
				rd=inst[11:7];
				alu_op={10{1'b1}};
				b_op={5{1'b1}};
				ls_op={5{1'b1}};
				// jal
				immr={{11{inst[31]}},inst[31],inst[19:12],inst[20],inst[30:21],1'b0};
				j_op=5'b00010;
			end
			// U-type decoder
			7'b0110111:begin
				rs1={5{1'b0}};
				rs2={5{1'b0}};
				rd=inst[11:7];
				alu_op={10{1'b1}};
				j_op={5{1'b1}};
				b_op={5{1'b1}};
				//lui
				immr={{12{inst[31]}},inst[31:12]};
				ls_op=5'b00100;
			end
			// U-type decoder
			7'b0010111:begin
				rs1={5{1'b0}};
				rs2={5{1'b0}};
				rd=inst[11:7];
				alu_op={10{1'b1}};
				j_op={5{1'b1}};
				b_op={5{1'b1}};
				// auipc
				immr={{12{inst[31]}},inst[31:12]};
				ls_op=5'b00101;
			end
			// S-type decoder
			// store
			7'b0100011:begin
				rs1=inst[19:15];
				rs2=inst[24:20];
				rd=inst[11:7];
				alu_op={10{1'b1}};
				j_op={5{1'b1}};
				b_op={5{1'b1}};
				case(inst[14:12])
					3'b000:begin // sb
						immr={{20{inst[31]}},inst[31:25],inst[11:7]};
						ls_op=5'b00110;
					end
					3'b001:begin // sh
						immr={{20{inst[31]}},inst[31:25],inst[11:7]};
						ls_op=5'b00111;
					end
					3'b010:begin // sw
						immr={{20{inst[31]}},inst[31:25],inst[11:7]};
						ls_op=5'b01000;
					end
				endcase
			end
			// B-type decoder
			7'b1100011:begin
				rs1=inst[19:15];
				rs2=inst[24:20];
				rd={5{1'b0}};
				alu_op={10{1'b1}};
				ls_op={5{1'b1}};
				j_op={5{1'b1}};
				case(inst[14:12])
					3'b000:begin // beq
						immr={{19{inst[31]}},inst[31],inst[7],inst[30:25],inst[11:8],1'b0};
						b_op=5'b00001;
					end
					3'b001:begin // bne
						immr={{19{inst[31]}},inst[31],inst[7],inst[30:25],inst[11:8],1'b0};
						b_op=5'b00010;
					end
					3'b100:begin // blt
						immr={{19{inst[31]}},inst[31],inst[7],inst[30:25],inst[11:8],1'b0};
						b_op=5'b00011;
					end
					3'b101:begin // bge
						immr={{19{inst[31]}},inst[31],inst[7],inst[30:25],inst[11:8],1'b0};
						b_op=5'b00100;
					end
					3'b110:begin // bltu
						immr={{19{inst[31]}},inst[31],inst[7],inst[30:25],inst[11:8],1'b0};
						b_op=5'b00101;
					end
					3'b111:begin // bgeu
						immr={{19{inst[31]}},inst[31],inst[7],inst[30:25],inst[11:8],1'b0};
						b_op=5'b00111;
					end
				endcase
			end
		endcase
	end

endmodule

DaVinci/Test_Decode_INST.v
/*
File Name   : Test_Decoder_INST.v
Description : RISC-V RV32I 译码器 测试
Written By  : Tealer Guo
Data        : 2019/04/29
*/
`timescale 1ns/1ns
module Test_Decoder_INST;
	// reg clk;
	reg[31:0] inst;

	wire[9:0] alu_op;
	wire[4:0] rs1;
	wire[4:0] rs2;
	wire[4:0] rd;
	wire[31:0] address_imm;
	wire[4:0] ls_op;
	wire[4:0] j_op;
	wire[4:0] b_op;

	Decode_INST test_decode_inst(
		// .clk(clk),
		.inst(inst),
		.alu_op(alu_op),
		.rs1(rs1),
		.rs2(rs2),
		.rd(rd),
		.address_imm(address_imm),
		.ls_op(ls_op),
		.j_op(j_op),
		.b_op(b_op)
		);

	initial begin
		// clk预留
		// #0 clk=0;inst=32'b01000000000100010000000110110011; // sub
		// #5 clk=1;
		// #5 clk=0;inst=32'b00000000001000001110010010110011; // or
		// #5 clk=1;
		// #5 clk=0;inst=32'b00000000110000111010000010110011; // slt
		// #5 clk=1;
		// #5 clk=0;inst=32'b10000111011000001100110010010011; // ori
		// #5 clk=1;
		// #5 clk=0;inst=32'b00101010110100011000111100000011; // lb
		// #5 clk=1;
		// #5 clk=0;inst=32'b00010101110011100000000011100111; // jalr
		// #5 clk=1;
		// #5 clk=0;inst=32'b00010101110100010110000101101111; // jal
		// #5 clk=1;
		// #5 clk=0;inst=32'b10111111010001011111110010110111; // lui
		// #5 clk=1;
		// #5 clk=0;inst=32'b11101110111001001010111100010111; // auipc
		// #5 clk=1;
		// #5 clk=0;inst=32'b11100101100111000001000110100011; // sh
		// #5 clk=1;
		// #5 clk=0;inst=32'b11101010000111010110000101100011; // bltu
		// #5 clk=1;
		// #10 $finish;
		#0 inst=32'b01000000000100010000000110110011; // sub
		#5 inst=32'b00000000001000001110010010110011; // or
		#5 inst=32'b00000000110000111010000010110011; // slt
		#5 inst=32'b10000111011000001100110010010011; // ori
		#5 inst=32'b00101010110100011000111100000011; // lb
		#5 inst=32'b00010101110011100000000011100111; // jalr
		#5 inst=32'b00010101110100010110000101101111; // jal
		#5 inst=32'b10111111010001011111110010110111; // lui
		#5 inst=32'b11101110111001001010111100010111; // auipc
		#5 inst=32'b11100101100111000001000110100011; // sh
		#5 inst=32'b11101010000111010110000101100011; // bltu
		#5 $finish; 
	end

	initial begin
		$dumpfile("Decode_INST.vcd");
		$dumpvars(0,Test_Decoder_INST);
	end

endmodule

DaVinci/Decode_INST.vcd
$date
	Mon Apr 29 17:26:00 2019
$end
$version
	Icarus Verilog
$end
$timescale
	1ns
$end
$scope module Test_Decoder_INST $end
$var wire 5 ! rs2 [4:0] $end
$var wire 5 " rs1 [4:0] $end
$var wire 5 # rd [4:0] $end
$var wire 5 $ ls_op [4:0] $end
$var wire 5 % j_op [4:0] $end
$var wire 5 & b_op [4:0] $end
$var wire 10 ' alu_op [9:0] $end
$var wire 32 ( address_imm [31:0] $end
$var reg 32 ) inst [31:0] $end
$scope module test_decode_inst $end
$var wire 32 * inst [31:0] $end
$var reg 32 + address_imm [31:0] $end
$var reg 10 , alu_op [9:0] $end
$var reg 5 - b_op [4:0] $end
$var reg 32 . immr [31:0] $end
$var reg 5 / j_op [4:0] $end
$var reg 5 0 ls_op [4:0] $end
$var reg 5 1 rd [4:0] $end
$var reg 5 2 rs1 [4:0] $end
$var reg 5 3 rs2 [4:0] $end
$upscope $end
$upscope $end
$enddefinitions $end
#0
$dumpvars
b1 3
b10 2
b11 1
b11111 0
b11111 /
b0 .
b11111 -
b10 ,
b0 +
b1000000000100010000000110110011 *
b1000000000100010000000110110011 )
b0 (
b10 '
b11111 &
b11111 %
b11111 $
b11 #
b10 "
b1 !
$end
#5
b1010 '
b1010 ,
b1001 #
b1001 1
b10 !
b10 3
b1 "
b1 2
b1000001110010010110011 )
b1000001110010010110011 *
#10
b101 '
b101 ,
b1 #
b1 1
b1100 !
b1100 3
b111 "
b111 2
b110000111010000010110011 )
b110000111010000010110011 *
#15
b11111111111111111111100001110110 (
b11111111111111111111100001110110 +
b11111111111111111111100001110110 .
b1000000111 '
b1000000111 ,
b11001 #
b11001 1
b0 !
b0 3
b1 "
b1 2
b10000111011000001100110010010011 )
b10000111011000001100110010010011 *
#20
b1010101101 (
b1010101101 +
b1 $
b1 0
b1010101101 .
b1111111111 '
b1111111111 ,
b1101 !
b1101 3
b11110 #
b11110 1
b11 "
b11 2
b101010110100011000111100000011 )
b101010110100011000111100000011 *
#25
b101011100 (
b101011100 +
b1 %
b1 /
b101011100 .
b11111 $
b11111 0
b1 #
b1 1
b0 !
b0 3
b11100 "
b11100 2
b10101110011100000000011100111 )
b10101110011100000000011100111 *
#30
b10110100101011100 (
b10110100101011100 +
b10 %
b10 /
b10110100101011100 .
b10 #
b10 1
b0 "
b0 2
b10101110100010110000101101111 )
b10101110100010110000101101111 *
#35
b11111111111110111111010001011111 (
b11111111111110111111010001011111 +
b100 $
b100 0
b11111111111110111111010001011111 .
b11111 %
b11111 /
b11001 #
b11001 1
b10111111010001011111110010110111 )
b10111111010001011111110010110111 *
#40
b11111111111111101110111001001010 (
b11111111111111101110111001001010 +
b101 $
b101 0
b11111111111111101110111001001010 .
b11110 #
b11110 1
b11101110111001001010111100010111 )
b11101110111001001010111100010111 *
#45
b11111111111111111111111001000011 (
b11111111111111111111111001000011 +
b111 $
b111 0
b11111111111111111111111001000011 .
b11 #
b11 1
b11001 !
b11001 3
b11000 "
b11000 2
b11100101100111000001000110100011 )
b11100101100111000001000110100011 *
#50
b11111111111111111111011010100010 (
b11111111111111111111011010100010 +
b101 &
b101 -
b11111111111111111111011010100010 .
b11111 $
b11111 0
b0 #
b0 1
b1 !
b1 3
b11010 "
b11010 2
b11101010000111010110000101100011 )
b11101010000111010110000101100011 *
