DaVinci/OLD/ALU.v
/*
File Name   : ALU.v
Description : RISC-V RV32I 算数逻辑单元
Written By  : Tealer Guo
Data        : 2019/04/20
*/
module ALU(
	input[31:0] rs1_num,
	input[31:0] rs2_num,
	// ALU操作数
	input[9:0] alu_op,
	// 结果输出
	output[31:0] rd_num
);
	// 实例化模块
	ALU_sched schedule(
		.rs1_num(rs1_num),
		.rs2_num(rs2_num),
		.alu_op(alu_op),
		.rd_num(rd_num)
	);
endmodule
// ALU调度
module ALU_sched(
	input[31:0] rs1_num,
	input[31:0] rs2_num,
	input[9:0] alu_op,
	// 单个rd_num输出
	output[31:0] rd_num,
	// add
	input[31:0] add_rs1,
	input[31:0] add_rs2,
	output[31:0] A_add_rd,
	// sub
	input[31:0] sub_rs1,
	input[31:0] sub_rs2,
	output[31:0] S_sub_rd,
	// sll
	input[31:0] sll_rs1,
	input[31:0] sll_rs2,
	output[31:0] SLL_sll_rd,
	// slt
	input[31:0] slt_rs1,
	input[31:0] slt_rs2,
	output[31:0] SLT_slt_rd,
	// sltu
	input[31:0] sltu_rs1,
	input[31:0] sltu_rs2,
	output[31:0] SLTU_sltu_rd,
	// xor
	input[31:0] xor_rs1,
	input[31:0] xor_rs2,
	output[31:0] X_xor_rd,
	// srl
	input[31:0] srl_rs1,
	input[31:0] srl_rs2,
	output[31:0] SRL_srl_rd,
	// sra
	input[31:0] sra_rs1,
	input[31:0] sra_rs2,
	output[31:0] SRA_sra_rd,
	// or
	input[31:0] or_rs1,
	input[31:0] or_rs2,
	output[31:0] O_or_rd,
	// and
	input[31:0] and_rs1,
	input[31:0] and_rs2,
	output[31:0] AND_and_rd
);
	// 实例化模块
	add_32 add_add(
		.add_rs1(rs1_num),
		.add_rs2(rs2_num),
		.add_rd(A_add_rd)
	);
	sub_32 sub_sub(
		.sub_rs1(rs1_num),
		.sub_rs2(rs2_num),
		.sub_rd(S_sub_rd)
	);
	sll_32 sll_sll(
		.sll_rs1(rs1_num),
		.sll_rs2(rs2_num),
		.sll_rd(SLL_sll_rd)
	);
	slt_32 slt_slt(
		.slt_rs1(rs1_num),
		.slt_rs2(rs2_num),
		.slt_rd(SLT_slt_rd)
	);
	sltu_32 sltu_sltu(
		.sltu_rs1(rs1_num),
		.sltu_rs2(rs2_num),
		.sltu_rd(SLTU_sltu_rd)
	);
	xor_32 xor_xor(
		.xor_rs1(rs1_num),
		.xor_rs2(rs2_num),
		.xor_rd(X_xor_rd)
	);
	srl_32 srl_srl(
		.srl_rs1(rs1_num),
		.srl_rs2(rs2_num),
		.srl_rd(SRL_srl_rd)
	);
	sra_32 sra_sra(
		.sra_rs1(rs1_num),
		.sra_rs2(rs2_num),
		.sra_rd(SRA_sra_rd)
	);
	or_32 or_or(
		.or_rs1(rs1_num),
		.or_rs2(rs2_num),
		.or_rd(O_or_rd)
	);
	and_32 and_and(
		.and_rs1(rs1_num),
		.and_rs2(rs2_num),
		.and_rd(AND_and_rd)
	);
	// 临时变量
	reg[31:0] rd_num_temp;
	// 多路选择器
	// add
	always @(*)
	begin
		if(alu_op===10'b0000000001)
			rd_num_temp=A_add_rd;
	end
	// sub
	always @(*)
	begin
		if(alu_op===10'b0000000010)
			rd_num_temp=S_sub_rd;
	end
	// sll
	always @(*)
	begin
		if(alu_op===10'b0000000011)
			rd_num_temp=SLL_sll_rd;
	end
	// slt
	always @(*)
	begin
		if(alu_op===10'b0000000101)
			rd_num_temp=SLT_slt_rd;
	end
	// sltu
	always @(*)
	begin
		if(alu_op===10'b0000000110)
			rd_num_temp=SLTU_sltu_rd;
	end
	// xor
	always @(*)
	begin
		if(alu_op===10'b0000000111)
			rd_num_temp=X_xor_rd;
	end
	// srl
	always @(*)
	begin
		if(alu_op===10'b0000001000)
			rd_num_temp=SRL_srl_rd;
	end
	// sra
	always @(*)
	begin
		if(alu_op===10'b0000001001)
			rd_num_temp=SRA_sra_rd;
	end
	// or
	always @(*)
	begin
		if(alu_op===10'b0000001010)
			rd_num_temp=O_or_rd;
	end
	// and
	always @(*)
	begin
		if(alu_op===10'b0000001011)
			rd_num_temp=AND_and_rd;
	end
	// 提交临时变量
	assign rd_num=rd_num_temp;
endmodule
// 加法
module add_32(
	input[31:0] add_rs1,
	input[31:0] add_rs2,
	output[31:0] add_rd
);
	assign add_rd=add_rs1+add_rs2;
endmodule
// 减法
module sub_32(
	input[31:0] sub_rs1,
	input[31:0] sub_rs2,
	output[31:0] sub_rd
);
	assign sub_rd=sub_rs1-sub_rs2;
endmodule
// 逻辑左移
module sll_32(
	input[31:0] sll_rs1,
	input[31:0] sll_rs2,
	output[31:0] sll_rd
);
	assign sll_rd=sll_rs1<<sll_rs2[4:0];
endmodule
// 小于则置位
module slt_32(
	input[31:0] slt_rs1,
	input[31:0] slt_rs2,
	output[31:0] slt_rd
);
	// 临时变量
	reg[31:0] slt_rd_temp;
	// MUX
	always @(*)
	begin
		if(slt_rs1<slt_rs2)
			slt_rd_temp=32'b11111111111111111111111111111111;
		else begin
			slt_rd_temp=32'b00000000000000000000000000000000;
		end
	end
	// 提交临时变量
	assign slt_rd=slt_rd_temp;
endmodule
// 无符号小于则置位
module sltu_32(
	input[31:0] sltu_rs1,
	input[31:0] sltu_rs2,
	output[31:0] sltu_rd
);
	// 临时变量
	reg[31:0] sltu_rd_temp;
	// MUX
	always @(*)
	begin
		if(sltu_rs1[30:0]<sltu_rs2[30:0])
			sltu_rd_temp=32'b11111111111111111111111111111111;
		else begin
			sltu_rd_temp=32'b00000000000000000000000000000000;
		end
	end
	// 提交临时变量
	assign sltu_rd=sltu_rd_temp;
endmodule
// 异或
module xor_32(
	input[31:0] xor_rs1,
	input[31:0] xor_rs2,
	output[31:0] xor_rd
);
	assign xor_rd=xor_rs1^xor_rs2;
endmodule
// 逻辑右移
module srl_32(
	input[31:0] srl_rs1,
	input[31:0] srl_rs2,
	output[31:0] srl_rd
);
	assign srl_rd=srl_rs1>>srl_rs2[4:0];
endmodule
// 算数右移
module sra_32(
	input[31:0] sra_rs1,
	input[31:0] sra_rs2,
	output[31:0] sra_rd
);
	assign sra_rd=($signed(sra_rs1))>>>sra_rs2[4:0];
endmodule
// 或
module or_32(
	input[31:0] or_rs1,
	input[31:0] or_rs2,
	output[31:0] or_rd
);
	assign or_rd=or_rs1|or_rs2;
endmodule
// 与
module and_32(
	input[31:0] and_rs1,
	input[31:0] and_rs2,
	output[31:0] and_rd
);
	assign and_rd=and_rs1&and_rs2;
endmodule

DaVinci/OLD/Test_ALU.v
/*
File Name   : Test_ALU.v
Description : RISC-V RV32I 算数逻辑单元 测试
Written By  : Tealer Guo
Data        : 2019/04/20
*/
`timescale 1ns/1ns
// 测试模块
module alu_test;
	reg[31:0] rs1_num;
	reg[31:0] rs2_num;
	// ALU操作数
	reg[9:0] alu_op;
	// 结果
	wire[31:0] rd_num;
	// 实例化模块
	ALU alu_test(
		.rs1_num(rs1_num),
		.rs2_num(rs2_num),
		.alu_op(alu_op),
		.rd_num(rd_num)
	);
	// 仿真设置
	// 32-bit 00000000000000000000000000000000
	initial
		begin
			#0 rs1_num=32'b00000000000010000010001010010110;rs2_num=32'b01000001111000010111100100110110;alu_op=10'b0000000001;//and
			#5 rs1_num=32'b01001100000010010010000100011010;rs2_num=32'b00000000001000010101100100110100;alu_op=10'b0000000010;//sub
			#5 rs1_num=32'b10000010010010010010100010011100;rs2_num=32'b00010001101001010000100000110010;alu_op=10'b0000001001;//sra
			#5 rs1_num=32'b00100010000010001010001000010110;rs2_num=32'b01010001011011111000100100110011;alu_op=10'b0000001010;//or
			#5 rs1_num=32'b00000100000010100010010010011000;rs2_num=32'b00110001001000010100100100111111;alu_op=10'b0000000001;//and
			#5 rs1_num=32'b00000000000010000010001010010110;rs2_num=32'b01000001111000010111100100110110;alu_op=10'b0000000011;//sll
			#5 rs1_num=32'b01001100000010010010000100011010;rs2_num=32'b00000000001000010101100100110100;alu_op=10'b0000000101;//slt
			#5 rs1_num=32'b00000010010010010010100010011100;rs2_num=32'b00010001101001010000100000110010;alu_op=10'b0000000110;//sltu
			#5 rs1_num=32'b00100010000010001010001000010110;rs2_num=32'b01010001011011111000100100110011;alu_op=10'b0000000111;//xor
			#5 rs1_num=32'b00000100000010100010010010011000;rs2_num=32'b00110001001000010100100100111111;alu_op=10'b0000001000;//srl
			#5 $finish;
		end
	// vvp设置
	initial
		begin
			$dumpfile("ALU.vcd");
			$dumpvars(0,alu_test);
		end

endmodule

DaVinci/OLD/ALU.vcd
$date
	Sat Apr 20 13:22:58 2019
$end
$version
	Icarus Verilog
$end
$timescale
	1ns
$end
$scope module alu_test $end
$scope module alu_test $end
$var wire 10 ! alu_op [9:0] $end
$var wire 32 " rs1_num [31:0] $end
$var wire 32 # rs2_num [31:0] $end
$var wire 32 $ rd_num [31:0] $end
$scope module schedule $end
$var wire 32 % add_rs1 [31:0] $end
$var wire 32 & add_rs2 [31:0] $end
$var wire 10 ' alu_op [9:0] $end
$var wire 32 ( and_rs1 [31:0] $end
$var wire 32 ) and_rs2 [31:0] $end
$var wire 32 * or_rs1 [31:0] $end
$var wire 32 + or_rs2 [31:0] $end
$var wire 32 , rd_num [31:0] $end
$var wire 32 - rs1_num [31:0] $end
$var wire 32 . rs2_num [31:0] $end
$var wire 32 / sll_rs1 [31:0] $end
$var wire 32 0 sll_rs2 [31:0] $end
$var wire 32 1 slt_rs1 [31:0] $end
$var wire 32 2 slt_rs2 [31:0] $end
$var wire 32 3 sltu_rs1 [31:0] $end
$var wire 32 4 sltu_rs2 [31:0] $end
$var wire 32 5 sra_rs1 [31:0] $end
$var wire 32 6 sra_rs2 [31:0] $end
$var wire 32 7 srl_rs1 [31:0] $end
$var wire 32 8 srl_rs2 [31:0] $end
$var wire 32 9 sub_rs1 [31:0] $end
$var wire 32 : sub_rs2 [31:0] $end
$var wire 32 ; xor_rs1 [31:0] $end
$var wire 32 < xor_rs2 [31:0] $end
$var wire 32 = X_xor_rd [31:0] $end
$var wire 32 > S_sub_rd [31:0] $end
$var wire 32 ? SRL_srl_rd [31:0] $end
$var wire 32 @ SRA_sra_rd [31:0] $end
$var wire 32 A SLT_slt_rd [31:0] $end
$var wire 32 B SLTU_sltu_rd [31:0] $end
$var wire 32 C SLL_sll_rd [31:0] $end
$var wire 32 D O_or_rd [31:0] $end
$var wire 32 E A_add_rd [31:0] $end
$var wire 32 F AND_and_rd [31:0] $end
$var reg 32 G rd_num_temp [31:0] $end
$scope module add_add $end
$var wire 32 H add_rs1 [31:0] $end
$var wire 32 I add_rs2 [31:0] $end
$var wire 32 J add_rd [31:0] $end
$upscope $end
$scope module and_and $end
$var wire 32 K and_rd [31:0] $end
$var wire 32 L and_rs1 [31:0] $end
$var wire 32 M and_rs2 [31:0] $end
$upscope $end
$scope module or_or $end
$var wire 32 N or_rd [31:0] $end
$var wire 32 O or_rs1 [31:0] $end
$var wire 32 P or_rs2 [31:0] $end
$upscope $end
$scope module sll_sll $end
$var wire 32 Q sll_rs1 [31:0] $end
$var wire 32 R sll_rs2 [31:0] $end
$var wire 32 S sll_rd [31:0] $end
$upscope $end
$scope module slt_slt $end
$var wire 32 T slt_rd [31:0] $end
$var wire 32 U slt_rs1 [31:0] $end
$var wire 32 V slt_rs2 [31:0] $end
$var reg 32 W slt_rd_temp [31:0] $end
$upscope $end
$scope module sltu_sltu $end
$var wire 32 X sltu_rd [31:0] $end
$var wire 32 Y sltu_rs1 [31:0] $end
$var wire 32 Z sltu_rs2 [31:0] $end
$var reg 32 [ sltu_rd_temp [31:0] $end
$upscope $end
$scope module sra_sra $end
$var wire 32 \ sra_rs1 [31:0] $end
$var wire 32 ] sra_rs2 [31:0] $end
$var wire 32 ^ sra_rd [31:0] $end
$upscope $end
$scope module srl_srl $end
$var wire 32 _ srl_rs1 [31:0] $end
$var wire 32 ` srl_rs2 [31:0] $end
$var wire 32 a srl_rd [31:0] $end
$upscope $end
$scope module sub_sub $end
$var wire 32 b sub_rs1 [31:0] $end
$var wire 32 c sub_rs2 [31:0] $end
$var wire 32 d sub_rd [31:0] $end
$upscope $end
$scope module xor_xor $end
$var wire 32 e xor_rd [31:0] $end
$var wire 32 f xor_rs1 [31:0] $end
$var wire 32 g xor_rs2 [31:0] $end
$upscope $end
$upscope $end
$upscope $end
$upscope $end
$enddefinitions $end
#0
$dumpvars
b1000001111000010111100100110110 g
b10000010001010010110 f
b1000001111010010101101110100000 e
b10111110001001101010100101100000 d
b1000001111000010111100100110110 c
b10000010001010010110 b
b0 a
b1000001111000010111100100110110 `
b10000010001010010110 _
b0 ^
b1000001111000010111100100110110 ]
b10000010001010010110 \
b11111111111111111111111111111111 [
b1000001111000010111100100110110 Z
b10000010001010010110 Y
b11111111111111111111111111111111 X
b11111111111111111111111111111111 W
b1000001111000010111100100110110 V
b10000010001010010110 U
b11111111111111111111111111111111 T
b10100101100000000000000000000000 S
b1000001111000010111100100110110 R
b10000010001010010110 Q
b1000001111000010111100100110110 P
b10000010001010010110 O
b1000001111010010111101110110110 N
b1000001111000010111100100110110 M
b10000010001010010110 L
b10000000010110 K
b1000001111010011001101111001100 J
b1000001111000010111100100110110 I
b10000010001010010110 H
b1000001111010011001101111001100 G
b10000000010110 F
b1000001111010011001101111001100 E
b1000001111010010111101110110110 D
b10100101100000000000000000000000 C
b11111111111111111111111111111111 B
b11111111111111111111111111111111 A
b0 @
b0 ?
b10111110001001101010100101100000 >
b1000001111010010101101110100000 =
bz <
bz ;
bz :
bz 9
bz 8
bz 7
bz 6
bz 5
bz 4
bz 3
bz 2
bz 1
bz 0
bz /
b1000001111000010111100100110110 .
b10000010001010010110 -
b1000001111010011001101111001100 ,
bz +
bz *
bz )
bz (
b1 '
bz &
bz %
b1000001111010011001101111001100 $
b1000001111000010111100100110110 #
b10000010001010010110 "
b1 !
$end
#5
b10000000100010000 F
b10000000100010000 K
b1001100001010010111100100111110 D
b1001100001010010111100100111110 N
b0 A
b0 T
b0 W
b0 B
b0 X
b0 [
b1001011111001111100011111100110 $
b1001011111001111100011111100110 ,
b1001011111001111100011111100110 G
b1001100001010000111100000101110 =
b1001100001010000111100000101110 e
b10 !
b10 '
b1000010101100100110100 #
b1000010101100100110100 .
b1000010101100100110100 I
b1000010101100100110100 M
b1000010101100100110100 P
b1000010101100100110100 R
b1000010101100100110100 V
b1000010101100100110100 Z
b1000010101100100110100 ]
b1000010101100100110100 `
b1000010101100100110100 c
b1000010101100100110100 g
b1001100001010100111101001001110 E
b1001100001010100111101001001110 J
b10001101000000000000000000000 C
b10001101000000000000000000000 S
b10011000000 @
b10011000000 ^
b10011000000 ?
b10011000000 a
b1001011111001111100011111100110 >
b1001011111001111100011111100110 d
b1001100000010010010000100011010 "
b1001100000010010010000100011010 -
b1001100000010010010000100011010 H
b1001100000010010010000100011010 L
b1001100000010010010000100011010 O
b1001100000010010010000100011010 Q
b1001100000010010010000100011010 U
b1001100000010010010000100011010 Y
b1001100000010010010000100011010 \
b1001100000010010010000100011010 _
b1001100000010010010000100011010 b
b1001100000010010010000100011010 f
#10
b10000100000010000 F
b10000100000010000 K
b10010011111011010010100010111110 D
b10010011111011010010100010111110 N
b11111111111111111111111111111111 B
b11111111111111111111111111111111 X
b11111111111111111111111111111111 [
b11111111111111111110000010010010 $
b11111111111111111110000010010010 ,
b11111111111111111110000010010010 G
b10010011111011000010000010101110 =
b10010011111011000010000010101110 e
b1001 !
b1001 '
b10001101001010000100000110010 #
b10001101001010000100000110010 .
b10001101001010000100000110010 I
b10001101001010000100000110010 M
b10001101001010000100000110010 P
b10001101001010000100000110010 R
b10001101001010000100000110010 V
b10001101001010000100000110010 Z
b10001101001010000100000110010 ]
b10001101001010000100000110010 `
b10001101001010000100000110010 c
b10001101001010000100000110010 g
b10010011111011100011000011001110 E
b10010011111011100011000011001110 J
b10100010011100000000000000000000 C
b10100010011100000000000000000000 S
b11111111111111111110000010010010 @
b11111111111111111110000010010010 ^
b10000010010010 ?
b10000010010010 a
b1110000101001000010000001101010 >
b1110000101001000010000001101010 d
b10000010010010010010100010011100 "
b10000010010010010010100010011100 -
b10000010010010010010100010011100 H
b10000010010010010010100010011100 L
b10000010010010010010100010011100 O
b10000010010010010010100010011100 Q
b10000010010010010010100010011100 U
b10000010010010010010100010011100 Y
b10000010010010010010100010011100 \
b10000010010010010010100010011100 _
b10000010010010010010100010011100 b
b10000010010010010010100010011100 f
#15
b1110011011011111010101100110111 $
b1110011011011111010101100110111 ,
b1110011011011111010101100110111 G
b10001000000000010010 F
b10001000000000010010 K
b1110011011011111010101100110111 D
b1110011011011111010101100110111 N
b11111111111111111111111111111111 A
b11111111111111111111111111111111 T
b11111111111111111111111111111111 W
b1110011011001110010101100100101 =
b1110011011001110010101100100101 e
b1010 !
b1010 '
b1010001011011111000100100110011 #
b1010001011011111000100100110011 .
b1010001011011111000100100110011 I
b1010001011011111000100100110011 M
b1010001011011111000100100110011 P
b1010001011011111000100100110011 R
b1010001011011111000100100110011 V
b1010001011011111000100100110011 Z
b1010001011011111000100100110011 ]
b1010001011011111000100100110011 `
b1010001011011111000100100110011 c
b1010001011011111000100100110011 g
b1110011011110000010101101001001 E
b1110011011110000010101101001001 J
b10000101100000000000000000000 C
b10000101100000000000000000000 S
b10001000001 @
b10001000001 ^
b10001000001 ?
b10001000001 a
b11010000100110010001100011100011 >
b11010000100110010001100011100011 d
b100010000010001010001000010110 "
b100010000010001010001000010110 -
b100010000010001010001000010110 H
b100010000010001010001000010110 L
b100010000010001010001000010110 O
b100010000010001010001000010110 Q
b100010000010001010001000010110 U
b100010000010001010001000010110 Y
b100010000010001010001000010110 \
b100010000010001010001000010110 _
b100010000010001010001000010110 b
b100010000010001010001000010110 f
#20
b110101001010110110110111010111 $
b110101001010110110110111010111 ,
b110101001010110110110111010111 G
b11000 F
b11000 K
b110101001010110110110110111111 D
b110101001010110110110110111111 N
b110101001010110110110110100111 =
b110101001010110110110110100111 e
b1 !
b1 '
b110001001000010100100100111111 #
b110001001000010100100100111111 .
b110001001000010100100100111111 I
b110001001000010100100100111111 M
b110001001000010100100100111111 P
b110001001000010100100100111111 R
b110001001000010100100100111111 V
b110001001000010100100100111111 Z
b110001001000010100100100111111 ]
b110001001000010100100100111111 `
b110001001000010100100100111111 c
b110001001000010100100100111111 g
b110101001010110110110111010111 E
b110101001010110110110111010111 J
b0 C
b0 S
b0 @
b0 ^
b0 ?
b0 a
b11010010111010001101101101011001 >
b11010010111010001101101101011001 d
b100000010100010010010011000 "
b100000010100010010010011000 -
b100000010100010010010011000 H
b100000010100010010010011000 L
b100000010100010010010011000 O
b100000010100010010010011000 Q
b100000010100010010010011000 U
b100000010100010010010011000 Y
b100000010100010010010011000 \
b100000010100010010010011000 _
b100000010100010010010011000 b
b100000010100010010010011000 f
#25
b10100101100000000000000000000000 $
b10100101100000000000000000000000 ,
b10100101100000000000000000000000 G
b10100101100000000000000000000000 C
b10100101100000000000000000000000 S
b10000000010110 F
b10000000010110 K
b1000001111010010111101110110110 D
b1000001111010010111101110110110 N
b1000001111010010101101110100000 =
b1000001111010010101101110100000 e
b11 !
b11 '
b1000001111000010111100100110110 #
b1000001111000010111100100110110 .
b1000001111000010111100100110110 I
b1000001111000010111100100110110 M
b1000001111000010111100100110110 P
b1000001111000010111100100110110 R
b1000001111000010111100100110110 V
b1000001111000010111100100110110 Z
b1000001111000010111100100110110 ]
b1000001111000010111100100110110 `
b1000001111000010111100100110110 c
b1000001111000010111100100110110 g
b1000001111010011001101111001100 E
b1000001111010011001101111001100 J
b10111110001001101010100101100000 >
b10111110001001101010100101100000 d
b10000010001010010110 "
b10000010001010010110 -
b10000010001010010110 H
b10000010001010010110 L
b10000010001010010110 O
b10000010001010010110 Q
b10000010001010010110 U
b10000010001010010110 Y
b10000010001010010110 \
b10000010001010010110 _
b10000010001010010110 b
b10000010001010010110 f
#30
b0 $
b0 ,
b0 G
b10000000100010000 F
b10000000100010000 K
b1001100001010010111100100111110 D
b1001100001010010111100100111110 N
b0 B
b0 X
b0 [
b0 A
b0 T
b0 W
b1001100001010000111100000101110 =
b1001100001010000111100000101110 e
b101 !
b101 '
b1000010101100100110100 #
b1000010101100100110100 .
b1000010101100100110100 I
b1000010101100100110100 M
b1000010101100100110100 P
b1000010101100100110100 R
b1000010101100100110100 V
b1000010101100100110100 Z
b1000010101100100110100 ]
b1000010101100100110100 `
b1000010101100100110100 c
b1000010101100100110100 g
b1001100001010100111101001001110 E
b1001100001010100111101001001110 J
b10001101000000000000000000000 C
b10001101000000000000000000000 S
b10011000000 @
b10011000000 ^
b10011000000 ?
b10011000000 a
b1001011111001111100011111100110 >
b1001011111001111100011111100110 d
b1001100000010010010000100011010 "
b1001100000010010010000100011010 -
b1001100000010010010000100011010 H
b1001100000010010010000100011010 L
b1001100000010010010000100011010 O
b1001100000010010010000100011010 Q
b1001100000010010010000100011010 U
b1001100000010010010000100011010 Y
b1001100000010010010000100011010 \
b1001100000010010010000100011010 _
b1001100000010010010000100011010 b
b1001100000010010010000100011010 f
#35
b11111111111111111111111111111111 $
b11111111111111111111111111111111 ,
b11111111111111111111111111111111 G
b10000100000010000 F
b10000100000010000 K
b10011111011010010100010111110 D
b10011111011010010100010111110 N
b11111111111111111111111111111111 A
b11111111111111111111111111111111 T
b11111111111111111111111111111111 W
b11111111111111111111111111111111 B
b11111111111111111111111111111111 X
b11111111111111111111111111111111 [
b10011111011000010000010101110 =
b10011111011000010000010101110 e
b110 !
b110 '
b10001101001010000100000110010 #
b10001101001010000100000110010 .
b10001101001010000100000110010 I
b10001101001010000100000110010 M
b10001101001010000100000110010 P
b10001101001010000100000110010 R
b10001101001010000100000110010 V
b10001101001010000100000110010 Z
b10001101001010000100000110010 ]
b10001101001010000100000110010 `
b10001101001010000100000110010 c
b10001101001010000100000110010 g
b10011111011100011000011001110 E
b10011111011100011000011001110 J
b10100010011100000000000000000000 C
b10100010011100000000000000000000 S
b10010010 @
b10010010 ^
b10010010 ?
b10010010 a
b11110000101001000010000001101010 >
b11110000101001000010000001101010 d
b10010010010010100010011100 "
b10010010010010100010011100 -
b10010010010010100010011100 H
b10010010010010100010011100 L
b10010010010010100010011100 O
b10010010010010100010011100 Q
b10010010010010100010011100 U
b10010010010010100010011100 Y
b10010010010010100010011100 \
b10010010010010100010011100 _
b10010010010010100010011100 b
b10010010010010100010011100 f
#40
b1110011011001110010101100100101 $
b1110011011001110010101100100101 ,
b1110011011001110010101100100101 G
b10001000000000010010 F
b10001000000000010010 K
b1110011011011111010101100110111 D
b1110011011011111010101100110111 N
b1110011011001110010101100100101 =
b1110011011001110010101100100101 e
b111 !
b111 '
b1010001011011111000100100110011 #
b1010001011011111000100100110011 .
b1010001011011111000100100110011 I
b1010001011011111000100100110011 M
b1010001011011111000100100110011 P
b1010001011011111000100100110011 R
b1010001011011111000100100110011 V
b1010001011011111000100100110011 Z
b1010001011011111000100100110011 ]
b1010001011011111000100100110011 `
b1010001011011111000100100110011 c
b1010001011011111000100100110011 g
b1110011011110000010101101001001 E
b1110011011110000010101101001001 J
b10000101100000000000000000000 C
b10000101100000000000000000000 S
b10001000001 @
b10001000001 ^
b10001000001 ?
b10001000001 a
b11010000100110010001100011100011 >
b11010000100110010001100011100011 d
b100010000010001010001000010110 "
b100010000010001010001000010110 -
b100010000010001010001000010110 H
b100010000010001010001000010110 L
b100010000010001010001000010110 O
b100010000010001010001000010110 Q
b100010000010001010001000010110 U
b100010000010001010001000010110 Y
b100010000010001010001000010110 \
b100010000010001010001000010110 _
b100010000010001010001000010110 b
b100010000010001010001000010110 f
#45
b11000 F
b11000 K
b110101001010110110110110111111 D
b110101001010110110110110111111 N
b0 $
b0 ,
b0 G
b110101001010110110110110100111 =
b110101001010110110110110100111 e
b1000 !
b1000 '
b110001001000010100100100111111 #
b110001001000010100100100111111 .
b110001001000010100100100111111 I
b110001001000010100100100111111 M
b110001001000010100100100111111 P
b110001001000010100100100111111 R
b110001001000010100100100111111 V
b110001001000010100100100111111 Z
b110001001000010100100100111111 ]
b110001001000010100100100111111 `
b110001001000010100100100111111 c
b110001001000010100100100111111 g
b110101001010110110110111010111 E
b110101001010110110110111010111 J
b0 C
b0 S
b0 @
b0 ^
b0 ?
b0 a
b11010010111010001101101101011001 >
b11010010111010001101101101011001 d
b100000010100010010010011000 "
b100000010100010010010011000 -
b100000010100010010010011000 H
b100000010100010010010011000 L
b100000010100010010010011000 O
b100000010100010010010011000 Q
b100000010100010010010011000 U
b100000010100010010010011000 Y
b100000010100010010010011000 \
b100000010100010010010011000 _
b100000010100010010010011000 b
b100000010100010010010011000 f
